bagelpay/__init__.py
bagelpay/client.py
bagelpay/exceptions.py
bagelpay/models.py
bagelpay-1.0.3.dist-info/METADATA
bagelpay-1.0.3.dist-info/WHEEL
bagelpay-1.0.3.dist-info/top_level.txt
bagelpay-1.0.3.dist-info/RECORD
