Metadata-Version: 2.4
Name: bagelpay
Version: 1.0.3
Summary: Official Python SDK for BagelPay payment processing
Home-page: https://github.com/bagelpay/bagelpay-sdk-python
Author: BagelPay
Author-email: BagelPay <support@bagelpayment.com>
License: MIT
Project-URL: Homepage, https://bagelpay.io
Project-URL: Documentation, https://bagelpay.gitbook.io/docs/documentation/sdks/python
Project-URL: Repository, https://github.com/bagelpay/bagelpay-sdk-python
Project-URL: Bug Reports, https://github.com/bagelpay/bagelpay-sdk-python/issues
Keywords: bagelpay,payment,sdk,api,fintech
Classifier: Development Status :: 4 - Beta
Classifier: Intended Audience :: Developers
Classifier: License :: OSI Approved :: MIT License
Classifier: Operating System :: OS Independent
Classifier: Programming Language :: Python :: 3
Classifier: Programming Language :: Python :: 3.8
Classifier: Programming Language :: Python :: 3.9
Classifier: Programming Language :: Python :: 3.10
Classifier: Programming Language :: Python :: 3.11
Classifier: Programming Language :: Python :: 3.12
Classifier: Topic :: Software Development :: Libraries :: Python Modules
Classifier: Topic :: Office/Business :: Financial
Requires-Python: >=3.7
Requires-Dist: requests>=2.25.0
Requires-Dist: urllib3>=1.26.0
Provides-Extra: dev
Requires-Dist: pytest>=7.0.0; extra == "dev"
Requires-Dist: pytest-cov>=4.0.0; extra == "dev"
Requires-Dist: black>=22.0.0; extra == "dev"
Requires-Dist: flake8>=5.0.0; extra == "dev"
Requires-Dist: mypy>=1.0.0; extra == "dev"
Dynamic: author
Dynamic: home-page
Dynamic: requires-python
